[
  {
    "ContainingType": "Shoesify.Apis.Controllers.AuthenticationController",
    "Method": "Login",
    "RelativePath": "api/Authentication/login",
    "HttpMethod": "POST",
    "IsController": true,
    "Order": 0,
    "Parameters": [
      {
        "Name": "request",
        "Type": "Shoesify.Services.Requests.LoginRequest",
        "IsRequired": true
      }
    ],
    "ReturnTypes": []
  },
  {
    "ContainingType": "Shoesify.Apis.Controllers.AuthenticationController",
    "Method": "Register",
    "RelativePath": "api/Authentication/register",
    "HttpMethod": "POST",
    "IsController": true,
    "Order": 0,
    "Parameters": [
      {
        "Name": "request",
        "Type": "Shoesify.Services.Requests.RegisterRequest",
        "IsRequired": true
      }
    ],
    "ReturnTypes": []
  },
  {
    "ContainingType": "Shoesify.Apis.Controllers.UserController",
    "Method": "GetAll",
    "RelativePath": "api/User/GetAllUsers",
    "HttpMethod": "GET",
    "IsController": true,
    "Order": 0,
    "Parameters": [],
    "ReturnTypes": []
  },
  {
    "ContainingType": "Shoesify.Apis.Controllers.UserController",
    "Method": "UpdateUserStatus",
    "RelativePath": "api/User/UpdateStatus",
    "HttpMethod": "PUT",
    "IsController": true,
    "Order": 0,
    "Parameters": [
      {
        "Name": "UserId",
        "Type": "System.String",
        "IsRequired": false
      },
      {
        "Name": "status",
        "Type": "System.Boolean",
        "IsRequired": false
      }
    ],
    "ReturnTypes": []
  },
  {
    "ContainingType": "Shoesify.Apis.Controllers.UserController",
    "Method": "UpdateUser",
    "RelativePath": "api/User/UpdateUser",
    "HttpMethod": "PUT",
    "IsController": true,
    "Order": 0,
    "Parameters": [
      {
        "Name": "userRequest",
        "Type": "Shoesify.Services.Requests.UpdateUserRequest",
        "IsRequired": true
      }
    ],
    "ReturnTypes": []
  }
]